pyNM/cf_matrix.py
pyNM/nonspiking_binary_classifier.py
pyNM/nonspiking_multiclass_classifier.py
pyNM/nonspiking_regressor.py
pyNM/spiking_binary_classifier.py
pyNM/spiking_multiclass_classifier.py
pyNM/spiking_regressor.py
pynmsnn-0.0.3.data/scripts/pynmsnn_package
pynmsnn-0.0.3.dist-info/METADATA
pynmsnn-0.0.3.dist-info/RECORD
pynmsnn-0.0.3.dist-info/WHEEL
pynmsnn-0.0.3.dist-info/top_level.txt
