Metadata-Version: 2.1
Name: pynmsnn
Version: 0.0.3
Summary: NeuroMorphic Predictive Model with Spiking Neural Networks (SNN) using Pytorch
Home-page: https://github.com/ajayarunachalam/pynmsnn/
Author: Ajay Arunachalam
Author-email: ajay.arunachalam08@gmail.com
License: UNKNOWN
Platform: UNKNOWN
Classifier: Programming Language :: Python :: 3
Classifier: License :: OSI Approved :: MIT License
Classifier: Operating System :: OS Independent
Requires-Dist: pandas
Requires-Dist: numpy
Requires-Dist: torch
Requires-Dist: seaborn
Requires-Dist: xgboost
Requires-Dist: scipy
Requires-Dist: tqdm
Requires-Dist: scikit-learn
Requires-Dist: matplotlib
Requires-Dist: plot-metric
Requires-Dist: regressormetricgraphplot
